<Properties StartupConfiguration="{1B61093B-E44F-AF59-25F3-EB2014FDA113}|">
  <MonoDevelop.Ide.Workbench ActiveDocument="Assets/Mizu/Scripts/Manager/SoundManager.cs">
    <Files>
      <File FileName="Assets/Mizu/Scripts/Manager/GameManager.cs" Line="61" Column="39" />
      <File FileName="Assets/Mizu/Scripts/Player/PlayerCat.cs" Line="52" Column="10" />
      <File FileName="Assets/Mizu/Scripts/Player/PlayerController.cs" Line="105" Column="40" />
      <File FileName="Assets/Mizu/Scripts/Other/GageUI.cs" Line="26" Column="10" />
      <File FileName="Assets/Mizu/Scripts/Manager/SoundManager.cs" Line="1" Column="1" />
    </Files>
    <Pads>
      <Pad Id="ProjectPad">
        <State name="__root__">
          <Node name="Running cat" expanded="True">
            <Node name="Assets" expanded="True">
              <Node name="Mizu" expanded="True">
                <Node name="Scripts" expanded="True">
                  <Node name="Manager" expanded="True">
                    <Node name="SoundManager.cs" selected="True" />
                  </Node>
                </Node>
              </Node>
            </Node>
          </Node>
        </State>
      </Pad>
    </Pads>
  </MonoDevelop.Ide.Workbench>
  <MonoDevelop.Ide.DebuggingService.PinnedWatches />
  <MonoDevelop.Ide.Workspace ActiveConfiguration="Debug" />
  <MonoDevelop.Ide.ItemProperties.Assembly-CSharp PreferredExecutionTarget="fa2d5ed8-7902-439a-a3f4-79186912c82b" />
  <MonoDevelop.Ide.DebuggingService.Breakpoints>
    <BreakpointStore />
  </MonoDevelop.Ide.DebuggingService.Breakpoints>
  <MultiItemStartupConfigurations />
</Properties>